[
  {
    "id": "_meta",
    "name": "Todesrätsel",
    "author": "Tommy"
  },
  {
    "id": "grandmother"
  },
  {
    "id": "pixie"
  },
  {
    "id": "sailor"
  },
  {
    "id": "balloonist"
  },
  {
    "id": "villageidiot"
  },
  {
    "id": "gambler"
  },
  {
    "id": "lycanthrope"
  },
  {
    "id": "engineer"
  },
  {
    "id": "professor"
  },
  {
    "id": "juggler"
  },
  {
    "id": "ravenkeeper"
  },
  {
    "id": "tealady"
  },
  {
    "id": "mayor"
  },
  {
    "id": "sweetheart"
  },
  {
    "id": "plaguedoctor"
  },
  {
    "id": "barber"
  },
  {
    "id": "hatter"
  },
  {
    "id": "devilsadvocate"
  },
  {
    "id": "assassin"
  },
  {
    "id": "xaan"
  },
  {
    "id": "boffin"
  },
  {
    "id": "shabaloth"
  },
  {
    "id": "zombuul"
  },
  {
    "id": "fanggu"
  },
  {
    "id": "lleech"
  }
]
