[
  {
    "id": "_meta",
    "logo": "https://i.postimg.cc/xCjR0s9n/monsters-in-my-mind-icon.png",
    "name": "Monsters In My Mind",
    "author": "Navean"
  },
  {
    "id": "chef"
  },
  {
    "id": "bountyhunter"
  },
  {
    "id": "pixie"
  },
  {
    "id": "preacher"
  },
  {
    "id": "fortuneteller"
  },
  {
    "id": "mathematician"
  },
  {
    "id": "oracle"
  },
  {
    "id": "innkeeper"
  },
  {
    "id": "amnesiac"
  },
  {
    "id": "seamstress"
  },
  {
    "id": "alchemist"
  },
  {
    "id": "sage"
  },
  {
    "id": "cannibal"
  },
  {
    "id": "recluse"
  },
  {
    "id": "mutant"
  },
  {
    "id": "drunk"
  },
  {
    "id": "lunatic"
  },
  {
    "id": "witch"
  },
  {
    "id": "cerenovus"
  },
  {
    "id": "fearmonger"
  },
  {
    "id": "goblin"
  },
  {
    "id": "pukka"
  },
  {
    "id": "nodashii"
  },
  {
    "id": "vortox"
  },
  {
    "id": "vigormortis"
  }
]
