[
  {
    "id": "_meta",
    "name": "H-erratic Behaviour",
    "author": "Fabb",
    "isOfficial": false
  },
  {
    "id": "noble"
  },
  {
    "id": "washerwoman"
  },
  {
    "id": "pixie"
  },
  {
    "id": "empath"
  },
  {
    "id": "highpriestess"
  },
  {
    "id": "balloonist"
  },
  {
    "id": "lycanthrope"
  },
  {
    "id": "savant"
  },
  {
    "id": "philosopher"
  },
  {
    "id": "huntsman"
  },
  {
    "id": "cannibal"
  },
  {
    "id": "amnesiac"
  },
  {
    "id": "farmer"
  },
  {
    "id": "banshee"
  },
  {
    "id": "politician"
  },
  {
    "id": "zealot"
  },
  {
    "id": "damsel"
  },
  {
    "id": "heretic"
  },
  {
    "id": "poisoner"
  },
  {
    "id": "harpy"
  },
  {
    "id": "cerenovus"
  },
  {
    "id": "goblin"
  },
  {
    "id": "scarletwoman"
  },
  {
    "id": "imp"
  },
  {
    "id": "kazali"
  }
]
