[
  {
    "id": "_meta",
    "name": "Volleybaby",
    "author": "Cozy Scriptwriting Corner (ft. Hallow)"
  },
  {
    "id": "chef"
  },
  {
    "id": "librarian"
  },
  {
    "id": "pixie"
  },
  {
    "id": "empath"
  },
  {
    "id": "highpriestess"
  },
  {
    "id": "villageidiot"
  },
  {
    "id": "king"
  },
  {
    "id": "fortuneteller"
  },
  {
    "id": "dreamer"
  },
  {
    "id": "towncrier"
  },
  {
    "id": "nightwatchman"
  },
  {
    "id": "artist"
  },
  {
    "id": "slayer"
  },
  {
    "id": "recluse"
  },
  {
    "id": "hatter"
  },
  {
    "id": "mutant"
  },
  {
    "id": "snitch"
  },
  {
    "id": "puzzlemaster"
  },
  {
    "id": "poisoner"
  },
  {
    "id": "spy"
  },
  {
    "id": "xaan"
  },
  {
    "id": "boomdandy"
  },
  {
    "id": "scarletwoman"
  },
  {
    "id": "lilmonsta"
  },
  {
    "id": "djinn"
  }
]
