[
  {
    "id": "_meta",
    "name": "Clockmaker’s Delight",
    "author": "Stoch (Mark)"
  },
  {
    "id": "washerwoman"
  },
  {
    "id": "clockmaker"
  },
  {
    "id": "librarian"
  },
  {
    "id": "empath"
  },
  {
    "id": "sailor"
  },
  {
    "id": "balloonist"
  },
  {
    "id": "chambermaid"
  },
  {
    "id": "fortuneteller"
  },
  {
    "id": "oracle"
  },
  {
    "id": "monk"
  },
  {
    "id": "seamstress"
  },
  {
    "id": "cannibal"
  },
  {
    "id": "fool"
  },
  {
    "id": "lunatic"
  },
  {
    "id": "drunk"
  },
  {
    "id": "recluse"
  },
  {
    "id": "hatter"
  },
  {
    "id": "poisoner"
  },
  {
    "id": "devilsadvocate"
  },
  {
    "id": "psychopath"
  },
  {
    "id": "marionette"
  },
  {
    "id": "lilmonsta"
  },
  {
    "id": "kazali"
  },
  {
    "id": "vortox"
  },
  {
    "id": "fanggu"
  }
]
