[
  {
    "id": "_meta",
    "name": "Planet Brouhaha",
    "author": "Cozy Scriptwriting Corner"
  },
  {
    "id": "noble"
  },
  {
    "id": "washerwoman"
  },
  {
    "id": "librarian"
  },
  {
    "id": "empath"
  },
  {
    "id": "towncrier"
  },
  {
    "id": "savant"
  },
  {
    "id": "nightwatchman"
  },
  {
    "id": "seamstress"
  },
  {
    "id": "huntsman"
  },
  {
    "id": "professor"
  },
  {
    "id": "slayer"
  },
  {
    "id": "fisherman"
  },
  {
    "id": "amnesiac"
  },
  {
    "id": "atheist"
  },
  {
    "id": "ogre"
  },
  {
    "id": "lunatic"
  },
  {
    "id": "damsel"
  },
  {
    "id": "puzzlemaster"
  },
  {
    "id": "spy"
  },
  {
    "id": "cerenovus"
  },
  {
    "id": "xaan"
  },
  {
    "id": "summoner"
  },
  {
    "id": "goblin"
  },
  {
    "id": "riot"
  }
]
