[
  {
    "id": "_meta",
    "name": "Catchphrase",
    "author": "Conrad"
  },
  {
    "id": "pixie"
  },
  {
    "id": "highpriestess"
  },
  {
    "id": "balloonist"
  },
  {
    "id": "villageidiot"
  },
  {
    "id": "snakecharmer"
  },
  {
    "id": "cultleader"
  },
  {
    "id": "lycanthrope"
  },
  {
    "id": "alsaahir"
  },
  {
    "id": "slayer"
  },
  {
    "id": "fisherman"
  },
  {
    "id": "juggler"
  },
  {
    "id": "alchemist"
  },
  {
    "id": "amnesiac"
  },
  {
    "id": "mayor"
  },
  {
    "id": "tinker"
  },
  {
    "id": "klutz"
  },
  {
    "id": "moonchild"
  },
  {
    "id": "saint"
  },
  {
    "id": "zealot"
  },
  {
    "id": "cerenovus"
  },
  {
    "id": "psychopath"
  },
  {
    "id": "widow"
  },
  {
    "id": "eviltwin"
  },
  {
    "id": "goblin"
  },
  {
    "id": "yaggababble"
  },
  {
    "id": "butcher"
  },
  {
    "id": "apprentice"
  },
  {
    "id": "beggar"
  },
  {
    "id": "deviant"
  },
  {
    "id": "gnome"
  },
  {
    "id": "sentinel"
  }
]
