[
  {
    "id": "_meta",
    "name": "Time to do Some Math",
    "author": "Sorbet_"
  },
  {
    "id": "king"
  },
  {
    "id": "washerwoman"
  },
  {
    "id": "mathematician"
  },
  {
    "id": "choirboy"
  },
  {
    "id": "seamstress"
  },
  {
    "id": "grandmother"
  },
  {
    "id": "general"
  },
  {
    "id": "empath"
  },
  {
    "id": "alsaahir"
  },
  {
    "id": "oracle"
  },
  {
    "id": "steward"
  },
  {
    "id": "chambermaid"
  },
  {
    "id": "moonchild"
  },
  {
    "id": "puzzlemaster"
  },
  {
    "id": "recluse"
  },
  {
    "id": "sweetheart"
  },
  {
    "id": "eviltwin"
  },
  {
    "id": "poisoner"
  },
  {
    "id": "godfather"
  },
  {
    "id": "cerenovus"
  },
  {
    "id": "yaggababble"
  },
  {
    "id": "imp"
  },
  {
    "id": "vigormortis"
  }
]
