[
  {
    "id": "_meta",
    "name": "Omninominations",
    "author": "Auto Psy"
  },
  {
    "id": "empath"
  },
  {
    "id": "sailor"
  },
  {
    "id": "king"
  },
  {
    "id": "flowergirl"
  },
  {
    "id": "towncrier"
  },
  {
    "id": "undertaker"
  },
  {
    "id": "cannibal"
  },
  {
    "id": "minstrel"
  },
  {
    "id": "choirboy"
  },
  {
    "id": "tealady"
  },
  {
    "id": "fool"
  },
  {
    "id": "virgin"
  },
  {
    "id": "butler"
  },
  {
    "id": "golem"
  },
  {
    "id": "saint"
  },
  {
    "id": "damsel"
  },
  {
    "id": "devilsadvocate"
  },
  {
    "id": "witch"
  },
  {
    "id": "fearmonger"
  },
  {
    "id": "goblin"
  },
  {
    "id": "mastermind"
  },
  {
    "id": "organgrinder"
  },
  {
    "id": "zombuul"
  },
  {
    "id": "vortox"
  },
  {
    "id": "lleech"
  },
  {
    "id": "bureaucrat"
  },
  {
    "id": "butcher"
  },
  {
    "id": "gnome"
  },
  {
    "id": "gunslinger"
  },
  {
    "id": "judge"
  },
  {
    "id": "beggar"
  },
  {
    "id": "djinn"
  },
  {
    "id": "ferryman"
  },
  {
    "id": "stormcatcher"
  }
]
