[
  {
    "id": "_meta",
    "name": "My first, my last, my... 1.2",
    "author": "Lilou"
  },
  {
    "id": "noble"
  },
  {
    "id": "shugenja"
  },
  {
    "id": "empath"
  },
  {
    "id": "dreamer"
  },
  {
    "id": "flowergirl"
  },
  {
    "id": "acrobat"
  },
  {
    "id": "exorcist"
  },
  {
    "id": "gossip"
  },
  {
    "id": "artist"
  },
  {
    "id": "farmer"
  },
  {
    "id": "mayor"
  },
  {
    "id": "monk"
  },
  {
    "id": "philosopher"
  },
  {
    "id": "drunk"
  },
  {
    "id": "recluse"
  },
  {
    "id": "klutz"
  },
  {
    "id": "goon"
  },
  {
    "id": "witch"
  },
  {
    "id": "poisoner"
  },
  {
    "id": "scarletwoman"
  },
  {
    "id": "assassin"
  },
  {
    "id": "nodashii"
  },
  {
    "id": "fanggu"
  },
  {
    "id": "imp"
  },
  {
    "id": "pukka"
  }
]
