[
  {
    "id": "_meta",
    "logo": "https://cdn-icons-png.flaticon.com/256/6426/6426815.png",
    "name": "Slithering Snakes",
    "author": "Alexis"
  },
  {
    "id": "steward"
  },
  {
    "id": "knight"
  },
  {
    "id": "empath"
  },
  {
    "id": "chambermaid"
  },
  {
    "id": "snakecharmer"
  },
  {
    "id": "dreamer"
  },
  {
    "id": "fortuneteller"
  },
  {
    "id": "monk"
  },
  {
    "id": "artist"
  },
  {
    "id": "fisherman"
  },
  {
    "id": "cannibal"
  },
  {
    "id": "ravenkeeper"
  },
  {
    "id": "pacifist"
  },
  {
    "id": "lunatic"
  },
  {
    "id": "drunk"
  },
  {
    "id": "damsel"
  },
  {
    "id": "heretic"
  },
  {
    "id": "psychopath"
  },
  {
    "id": "goblin"
  },
  {
    "id": "boomdandy"
  },
  {
    "id": "vizier"
  },
  {
    "id": "pukka"
  },
  {
    "id": "nodashii"
  },
  {
    "id": "vortox"
  },
  {
    "id": "lleech"
  },
  {
    "id": "barista"
  },
  {
    "id": "matron"
  },
  {
    "id": "bonecollector"
  },
  {
    "id": "scapegoat"
  },
  {
    "id": "gnome"
  },
  {
    "id": "sentinel"
  }
]
