[
  {
    "id": "_meta",
    "name": "Dumpster Fire!",
    "author": "Off Meta"
  },
  {
    "id": "librarian"
  },
  {
    "id": "sailor"
  },
  {
    "id": "gambler"
  },
  {
    "id": "seamstress"
  },
  {
    "id": "professor"
  },
  {
    "id": "juggler"
  },
  {
    "id": "pacifist"
  },
  {
    "id": "ravenkeeper"
  },
  {
    "id": "huntsman"
  },
  {
    "id": "king"
  },
  {
    "id": "choirboy"
  },
  {
    "id": "atheist"
  },
  {
    "id": "farmer"
  },
  {
    "id": "mutant"
  },
  {
    "id": "heretic"
  },
  {
    "id": "politician"
  },
  {
    "id": "damsel"
  },
  {
    "id": "lunatic"
  },
  {
    "id": "godfather"
  },
  {
    "id": "assassin"
  },
  {
    "id": "poisoner"
  },
  {
    "id": "pithag"
  },
  {
    "id": "zombuul"
  },
  {
    "id": "vortox"
  },
  {
    "id": "shabaloth"
  }
]
