[
  {
    "id": "_meta",
    "name": "Virus Nyeh Detected, Eeevrything Goodski",
    "author": "Brad Fortner"
  },
  {
    "id": "engineer"
  },
  {
    "id": "noble"
  },
  {
    "id": "chambermaid"
  },
  {
    "id": "oracle"
  },
  {
    "id": "dreamer"
  },
  {
    "id": "exorcist"
  },
  {
    "id": "puzzlemaster"
  },
  {
    "id": "plaguedoctor"
  },
  {
    "id": "hermit"
  },
  {
    "id": "xaan"
  },
  {
    "id": "boffin"
  },
  {
    "id": "mastermind"
  },
  {
    "id": "vortox"
  },
  {
    "id": "lleech"
  }
]
