[
  {
    "id": "_meta",
    "name": "Trouble Troubling",
    "author": "RobT"
  },
  {
    "id": "knight"
  },
  {
    "id": "chef"
  },
  {
    "id": "noble"
  },
  {
    "id": "washerwoman"
  },
  {
    "id": "empath"
  },
  {
    "id": "balloonist"
  },
  {
    "id": "undertaker"
  },
  {
    "id": "seamstress"
  },
  {
    "id": "slayer"
  },
  {
    "id": "soldier"
  },
  {
    "id": "ravenkeeper"
  },
  {
    "id": "mayor"
  },
  {
    "id": "virgin"
  },
  {
    "id": "ogre"
  },
  {
    "id": "lunatic"
  },
  {
    "id": "drunk"
  },
  {
    "id": "recluse"
  },
  {
    "id": "saint"
  },
  {
    "id": "poisoner"
  },
  {
    "id": "spy"
  },
  {
    "id": "marionette"
  },
  {
    "id": "scarletwoman"
  },
  {
    "id": "baron"
  },
  {
    "id": "imp"
  },
  {
    "id": "vortox"
  }
]
