[
  {
    "id": "_meta",
    "name": "TB + Fang Gu + Philo + Klutz",
    "author": "BOTC Kolkata"
  },
  {
    "id": "chef"
  },
  {
    "id": "investigator"
  },
  {
    "id": "washerwoman"
  },
  {
    "id": "librarian"
  },
  {
    "id": "empath"
  },
  {
    "id": "fortuneteller"
  },
  {
    "id": "undertaker"
  },
  {
    "id": "monk"
  },
  {
    "id": "slayer"
  },
  {
    "id": "soldier"
  },
  {
    "id": "ravenkeeper"
  },
  {
    "id": "mayor"
  },
  {
    "id": "virgin"
  },
  {
    "id": "philosopher"
  },
  {
    "id": "butler"
  },
  {
    "id": "drunk"
  },
  {
    "id": "recluse"
  },
  {
    "id": "saint"
  },
  {
    "id": "klutz"
  },
  {
    "id": "poisoner"
  },
  {
    "id": "spy"
  },
  {
    "id": "scarletwoman"
  },
  {
    "id": "baron"
  },
  {
    "id": "imp"
  },
  {
    "id": "fanggu"
  }
]
