[
  {
    "id": "_meta",
    "name": "Life and death are fated",
    "author": "Oyyko"
  },
  {
    "id": "empath"
  },
  {
    "id": "librarian"
  },
  {
    "id": "fool"
  },
  {
    "id": "sailor"
  },
  {
    "id": "pacifist"
  },
  {
    "id": "savant"
  },
  {
    "id": "mathematician"
  },
  {
    "id": "seamstress"
  },
  {
    "id": "pixie"
  },
  {
    "id": "farmer"
  },
  {
    "id": "noble"
  },
  {
    "id": "slayer"
  },
  {
    "id": "fortuneteller"
  },
  {
    "id": "recluse"
  },
  {
    "id": "drunk"
  },
  {
    "id": "saint"
  },
  {
    "id": "mutant"
  },
  {
    "id": "scarletwoman"
  },
  {
    "id": "spy"
  },
  {
    "id": "goblin"
  },
  {
    "id": "organgrinder"
  },
  {
    "id": "alhadikhia"
  },
  {
    "id": "nodashii"
  },
  {
    "id": "pukka"
  },
  {
    "id": "imp"
  }
]
