[
  {
    "id": "_meta",
    "name": "Circles of Salt",
    "author": "Harbor"
  },
  {
    "id": "noble"
  },
  {
    "id": "shugenja"
  },
  {
    "id": "highpriestess"
  },
  {
    "id": "balloonist"
  },
  {
    "id": "villageidiot"
  },
  {
    "id": "monk"
  },
  {
    "id": "acrobat"
  },
  {
    "id": "savant"
  },
  {
    "id": "alsaahir"
  },
  {
    "id": "fisherman"
  },
  {
    "id": "princess"
  },
  {
    "id": "amnesiac"
  },
  {
    "id": "ravenkeeper"
  },
  {
    "id": "goon"
  },
  {
    "id": "drunk"
  },
  {
    "id": "tinker"
  },
  {
    "id": "plaguedoctor"
  },
  {
    "id": "godfather"
  },
  {
    "id": "harpy"
  },
  {
    "id": "witch"
  },
  {
    "id": "xaan"
  },
  {
    "id": "summoner"
  },
  {
    "id": "yaggababble"
  },
  {
    "id": "pukka"
  },
  {
    "id": "imp"
  }
]
