[
  {
    "id": "_meta",
    "name": "Off With The Head",
    "author": "Ocean",
    "bootlegger": [
      "The Widow/Damsel jinx is rewritten; 'If the Widow sees the Grimoire (once), the Damsel is poisoned.'"
    ]
  },
  {
    "id": "knight"
  },
  {
    "id": "pixie"
  },
  {
    "id": "bountyhunter"
  },
  {
    "id": "balloonist"
  },
  {
    "id": "preacher"
  },
  {
    "id": "king"
  },
  {
    "id": "alsaahir"
  },
  {
    "id": "engineer"
  },
  {
    "id": "huntsman"
  },
  {
    "id": "choirboy"
  },
  {
    "id": "banshee"
  },
  {
    "id": "mayor"
  },
  {
    "id": "poppygrower"
  },
  {
    "id": "hatter"
  },
  {
    "id": "zealot"
  },
  {
    "id": "damsel"
  },
  {
    "id": "puzzlemaster"
  },
  {
    "id": "psychopath"
  },
  {
    "id": "widow"
  },
  {
    "id": "goblin"
  },
  {
    "id": "organgrinder"
  },
  {
    "id": "imp"
  },
  {
    "id": "ojo"
  },
  {
    "id": "vigormortis"
  },
  {
    "id": "lleech"
  },
  {
    "id": "thief"
  },
  {
    "id": "bureaucrat"
  },
  {
    "id": "butcher"
  },
  {
    "id": "bonecollector"
  },
  {
    "id": "deviant"
  },
  {
    "id": "djinn"
  }
]
