[
  {
    "id": "_meta",
    "name": "Abyssal Waltz",
    "author": "CocoBun"
  },
  {
    "id": "steward"
  },
  {
    "id": "investigator"
  },
  {
    "id": "clockmaker"
  },
  {
    "id": "bountyhunter"
  },
  {
    "id": "chambermaid"
  },
  {
    "id": "snakecharmer"
  },
  {
    "id": "king"
  },
  {
    "id": "monk"
  },
  {
    "id": "savant"
  },
  {
    "id": "alsaahir"
  },
  {
    "id": "philosopher"
  },
  {
    "id": "cannibal"
  },
  {
    "id": "choirboy"
  },
  {
    "id": "barber"
  },
  {
    "id": "hatter"
  },
  {
    "id": "snitch"
  },
  {
    "id": "puzzlemaster"
  },
  {
    "id": "cerenovus"
  },
  {
    "id": "pithag"
  },
  {
    "id": "marionette"
  },
  {
    "id": "mastermind"
  },
  {
    "id": "lilmonsta"
  },
  {
    "id": "imp"
  },
  {
    "id": "fanggu"
  },
  {
    "id": "spiritofivory"
  }
]
