[
  {
    "id": "_meta",
    "name": "New and Unthreatening",
    "author": "Brendan"
  },
  {
    "id": "noble"
  },
  {
    "id": "pixie"
  },
  {
    "id": "bountyhunter"
  },
  {
    "id": "empath"
  },
  {
    "id": "balloonist"
  },
  {
    "id": "snakecharmer"
  },
  {
    "id": "cultleader"
  },
  {
    "id": "gossip"
  },
  {
    "id": "philosopher"
  },
  {
    "id": "huntsman"
  },
  {
    "id": "artist"
  },
  {
    "id": "amnesiac"
  },
  {
    "id": "poppygrower"
  },
  {
    "id": "drunk"
  },
  {
    "id": "plaguedoctor"
  },
  {
    "id": "barber"
  },
  {
    "id": "damsel"
  },
  {
    "id": "poisoner"
  },
  {
    "id": "fearmonger"
  },
  {
    "id": "psychopath"
  },
  {
    "id": "wizard"
  },
  {
    "id": "organgrinder"
  },
  {
    "id": "yaggababble"
  },
  {
    "id": "lilmonsta"
  },
  {
    "id": "kazali"
  },
  {
    "id": "legion"
  },
  {
    "id": "bigwig"
  }
]
