[
  {
    "id": "_meta",
    "name": "Twin Town",
    "author": "Qaday",
    "bootlegger": [
      "The Boffin may give the Demon an in-play townsfolk ability, and will know it is in play.",
      "The Pit Hag's ability may still work if there is only 1 of the chosen good character in play.",
      "There may be at most 2 of the same townsfolk in play."
    ]
  },
  {
    "id": "washerwoman"
  },
  {
    "id": "pixie"
  },
  {
    "id": "villageidiot"
  },
  {
    "id": "snakecharmer"
  },
  {
    "id": "dreamer"
  },
  {
    "id": "alsaahir"
  },
  {
    "id": "philosopher"
  },
  {
    "id": "huntsman"
  },
  {
    "id": "slayer"
  },
  {
    "id": "alchemist"
  },
  {
    "id": "cannibal"
  },
  {
    "id": "amnesiac"
  },
  {
    "id": "farmer"
  },
  {
    "id": "lunatic"
  },
  {
    "id": "drunk"
  },
  {
    "id": "mutant"
  },
  {
    "id": "damsel"
  },
  {
    "id": "cerenovus"
  },
  {
    "id": "pithag"
  },
  {
    "id": "eviltwin"
  },
  {
    "id": "scarletwoman"
  },
  {
    "id": "boffin"
  },
  {
    "id": "pukka"
  },
  {
    "id": "kazali"
  },
  {
    "id": "vigormortis"
  },
  {
    "id": "fanggu"
  },
  {
    "id": "bootlegger"
  }
]
