[
  {
    "id": "_meta",
    "name": "Fear and Faith",
    "author": "Rippythegator"
  },
  {
    "id": "grandmother"
  },
  {
    "id": "shugenja"
  },
  {
    "id": "bountyhunter"
  },
  {
    "id": "preacher"
  },
  {
    "id": "chambermaid"
  },
  {
    "id": "snakecharmer"
  },
  {
    "id": "cultleader"
  },
  {
    "id": "flowergirl"
  },
  {
    "id": "alsaahir"
  },
  {
    "id": "professor"
  },
  {
    "id": "ravenkeeper"
  },
  {
    "id": "banshee"
  },
  {
    "id": "mayor"
  },
  {
    "id": "drunk"
  },
  {
    "id": "plaguedoctor"
  },
  {
    "id": "saint"
  },
  {
    "id": "hatter"
  },
  {
    "id": "zealot"
  },
  {
    "id": "harpy"
  },
  {
    "id": "witch"
  },
  {
    "id": "fearmonger"
  },
  {
    "id": "xaan"
  },
  {
    "id": "goblin"
  },
  {
    "id": "alhadikhia"
  },
  {
    "id": "bigwig"
  }
]
