[
  {
    "id": "_meta",
    "name": "Mr. Rogers' Neighborhood",
    "author": "Courage"
  },
  {
    "id": "chef"
  },
  {
    "id": "grandmother"
  },
  {
    "id": "shugenja"
  },
  {
    "id": "empath"
  },
  {
    "id": "sailor"
  },
  {
    "id": "dreamer"
  },
  {
    "id": "cultleader"
  },
  {
    "id": "professor"
  },
  {
    "id": "minstrel"
  },
  {
    "id": "tealady"
  },
  {
    "id": "fool"
  },
  {
    "id": "magician"
  },
  {
    "id": "pacifist"
  },
  {
    "id": "hermit"
  },
  {
    "id": "goon"
  },
  {
    "id": "klutz"
  },
  {
    "id": "puzzlemaster"
  },
  {
    "id": "spy"
  },
  {
    "id": "psychopath"
  },
  {
    "id": "marionette"
  },
  {
    "id": "eviltwin"
  },
  {
    "id": "nodashii"
  },
  {
    "id": "kazali"
  },
  {
    "id": "legion"
  },
  {
    "id": "lordoftyphon"
  }
]
