[
  {
    "id": "_meta",
    "name": "I'll handle this",
    "author": "The Honeyman"
  },
  {
    "id": "chef"
  },
  {
    "id": "investigator"
  },
  {
    "id": "pixie"
  },
  {
    "id": "bountyhunter"
  },
  {
    "id": "empath"
  },
  {
    "id": "balloonist"
  },
  {
    "id": "oracle"
  },
  {
    "id": "undertaker"
  },
  {
    "id": "gossip"
  },
  {
    "id": "minstrel"
  },
  {
    "id": "sage"
  },
  {
    "id": "fool"
  },
  {
    "id": "pacifist"
  },
  {
    "id": "drunk"
  },
  {
    "id": "recluse"
  },
  {
    "id": "sweetheart"
  },
  {
    "id": "mutant"
  },
  {
    "id": "snitch"
  },
  {
    "id": "spy"
  },
  {
    "id": "xaan"
  },
  {
    "id": "boomdandy"
  },
  {
    "id": "scarletwoman"
  },
  {
    "id": "boffin"
  },
  {
    "id": "yaggababble"
  },
  {
    "id": "lilmonsta"
  },
  {
    "id": "barista"
  },
  {
    "id": "apprentice"
  },
  {
    "id": "deviant"
  },
  {
    "id": "scapegoat"
  }
]
