[
  {
    "id": "_meta",
    "name": "Moral Decay",
    "author": "KingoftheAbyss"
  },
  {
    "id": "librarian"
  },
  {
    "id": "pixie"
  },
  {
    "id": "bountyhunter"
  },
  {
    "id": "balloonist"
  },
  {
    "id": "snakecharmer"
  },
  {
    "id": "mathematician"
  },
  {
    "id": "dreamer"
  },
  {
    "id": "cultleader"
  },
  {
    "id": "lycanthrope"
  },
  {
    "id": "nightwatchman"
  },
  {
    "id": "philosopher"
  },
  {
    "id": "alchemist"
  },
  {
    "id": "farmer"
  },
  {
    "id": "hermit"
  },
  {
    "id": "goon"
  },
  {
    "id": "ogre"
  },
  {
    "id": "lunatic"
  },
  {
    "id": "politician"
  },
  {
    "id": "mezepheles"
  },
  {
    "id": "pithag"
  },
  {
    "id": "marionette"
  },
  {
    "id": "mastermind"
  },
  {
    "id": "legion"
  },
  {
    "id": "fanggu"
  },
  {
    "id": "lordoftyphon"
  }
]
