[
  {
    "id": "_meta",
    "name": "Wagon Wheel Watusi",
    "author": "Pants McGee"
  },
  {
    "id": "steward"
  },
  {
    "id": "shugenja"
  },
  {
    "id": "balloonist"
  },
  {
    "id": "dreamer"
  },
  {
    "id": "oracle"
  },
  {
    "id": "monk"
  },
  {
    "id": "gossip"
  },
  {
    "id": "philosopher"
  },
  {
    "id": "alchemist"
  },
  {
    "id": "farmer"
  },
  {
    "id": "tealady"
  },
  {
    "id": "fool"
  },
  {
    "id": "poppygrower"
  },
  {
    "id": "drunk"
  },
  {
    "id": "sweetheart"
  },
  {
    "id": "barber"
  },
  {
    "id": "zealot"
  },
  {
    "id": "devilsadvocate"
  },
  {
    "id": "pithag"
  },
  {
    "id": "marionette"
  },
  {
    "id": "goblin"
  },
  {
    "id": "vortox"
  },
  {
    "id": "legion"
  },
  {
    "id": "lleech"
  }
]
