[
  {
    "id": "_meta",
    "name": "Kinda Sus?",
    "author": "Unemployed Turtle"
  },
  {
    "id": "noble"
  },
  {
    "id": "grandmother"
  },
  {
    "id": "empath"
  },
  {
    "id": "chambermaid"
  },
  {
    "id": "fortuneteller"
  },
  {
    "id": "undertaker"
  },
  {
    "id": "monk"
  },
  {
    "id": "savant"
  },
  {
    "id": "nightwatchman"
  },
  {
    "id": "artist"
  },
  {
    "id": "ravenkeeper"
  },
  {
    "id": "virgin"
  },
  {
    "id": "poppygrower"
  },
  {
    "id": "ogre"
  },
  {
    "id": "drunk"
  },
  {
    "id": "recluse"
  },
  {
    "id": "saint"
  },
  {
    "id": "poisoner"
  },
  {
    "id": "spy"
  },
  {
    "id": "cerenovus"
  },
  {
    "id": "goblin"
  },
  {
    "id": "imp"
  },
  {
    "id": "kazali"
  }
]
