[
  {
    "id": "_meta",
    "name": "Job 13:5",
    "author": "[REDACTED]"
  },
  {
    "id": "noble"
  },
  {
    "id": "investigator"
  },
  {
    "id": "snakecharmer"
  },
  {
    "id": "dreamer"
  },
  {
    "id": "flowergirl"
  },
  {
    "id": "undertaker"
  },
  {
    "id": "courtier"
  },
  {
    "id": "princess"
  },
  {
    "id": "alchemist"
  },
  {
    "id": "sage"
  },
  {
    "id": "virgin"
  },
  {
    "id": "poppygrower"
  },
  {
    "id": "atheist"
  },
  {
    "id": "drunk"
  },
  {
    "id": "recluse"
  },
  {
    "id": "heretic"
  },
  {
    "id": "puzzlemaster"
  },
  {
    "id": "witch"
  },
  {
    "id": "fearmonger"
  },
  {
    "id": "assassin"
  },
  {
    "id": "eviltwin"
  },
  {
    "id": "vizier"
  },
  {
    "id": "imp"
  },
  {
    "id": "po"
  },
  {
    "id": "vortox"
  },
  {
    "id": "fanggu"
  }
]
