[
  {
    "id": "_meta",
    "name": "Bigger Than Yours",
    "author": "Cam",
    "bootlegger": [
      "If a puzzledrunk player becomes an evil Demon, the Storyteller might make a different player become an evil Demon instead."
    ]
  },
  {
    "id": "grandmother"
  },
  {
    "id": "librarian"
  },
  {
    "id": "pixie"
  },
  {
    "id": "balloonist"
  },
  {
    "id": "dreamer"
  },
  {
    "id": "undertaker"
  },
  {
    "id": "monk"
  },
  {
    "id": "gambler"
  },
  {
    "id": "acrobat"
  },
  {
    "id": "gossip"
  },
  {
    "id": "artist"
  },
  {
    "id": "fisherman"
  },
  {
    "id": "farmer"
  },
  {
    "id": "hermit"
  },
  {
    "id": "drunk"
  },
  {
    "id": "tinker"
  },
  {
    "id": "puzzlemaster"
  },
  {
    "id": "godfather"
  },
  {
    "id": "spy"
  },
  {
    "id": "cerenovus"
  },
  {
    "id": "assassin"
  },
  {
    "id": "summoner"
  },
  {
    "id": "imp"
  },
  {
    "id": "ojo"
  },
  {
    "id": "po"
  },
  {
    "id": "bootlegger"
  }
]
