[
  {
    "id": "_meta",
    "name": "Any%",
    "author": "George"
  },
  {
    "id": "investigator"
  },
  {
    "id": "washerwoman"
  },
  {
    "id": "pixie"
  },
  {
    "id": "empath"
  },
  {
    "id": "dreamer"
  },
  {
    "id": "snakecharmer"
  },
  {
    "id": "amnesiac"
  },
  {
    "id": "juggler"
  },
  {
    "id": "professor"
  },
  {
    "id": "philosopher"
  },
  {
    "id": "alchemist"
  },
  {
    "id": "poppygrower"
  },
  {
    "id": "cannibal"
  },
  {
    "id": "acrobat"
  },
  {
    "id": "sweetheart"
  },
  {
    "id": "heretic"
  },
  {
    "id": "drunk"
  },
  {
    "id": "lunatic"
  },
  {
    "id": "widow"
  },
  {
    "id": "poisoner"
  },
  {
    "id": "baron"
  },
  {
    "id": "goblin"
  },
  {
    "id": "boomdandy"
  },
  {
    "id": "shabaloth"
  },
  {
    "id": "legion"
  }
]
