[
  {
    "id": "_meta",
    "name": "Experimental only",
    "author": "Helle"
  },
  {
    "id": "steward"
  },
  {
    "id": "knight"
  },
  {
    "id": "pixie"
  },
  {
    "id": "bountyhunter"
  },
  {
    "id": "balloonist"
  },
  {
    "id": "cultleader"
  },
  {
    "id": "lycanthrope"
  },
  {
    "id": "huntsman"
  },
  {
    "id": "amnesiac"
  },
  {
    "id": "alchemist"
  },
  {
    "id": "farmer"
  },
  {
    "id": "magician"
  },
  {
    "id": "cannibal"
  },
  {
    "id": "damsel"
  },
  {
    "id": "golem"
  },
  {
    "id": "heretic"
  },
  {
    "id": "puzzlemaster"
  },
  {
    "id": "fearmonger"
  },
  {
    "id": "mezepheles"
  },
  {
    "id": "boomdandy"
  },
  {
    "id": "psychopath"
  },
  {
    "id": "goblin"
  },
  {
    "id": "alhadikhia"
  },
  {
    "id": "lilmonsta"
  },
  {
    "id": "lleech"
  }
]
