[
  {
    "id": "_meta",
    "name": "Accounting for Everyone",
    "author": "Zadon"
  },
  {
    "id": "investigator"
  },
  {
    "id": "knight"
  },
  {
    "id": "steward"
  },
  {
    "id": "king"
  },
  {
    "id": "dreamer"
  },
  {
    "id": "innkeeper"
  },
  {
    "id": "oracle"
  },
  {
    "id": "alchemist"
  },
  {
    "id": "amnesiac"
  },
  {
    "id": "seamstress"
  },
  {
    "id": "huntsman"
  },
  {
    "id": "choirboy"
  },
  {
    "id": "poppygrower"
  },
  {
    "id": "drunk"
  },
  {
    "id": "goon"
  },
  {
    "id": "sweetheart"
  },
  {
    "id": "mutant"
  },
  {
    "id": "damsel"
  },
  {
    "id": "godfather"
  },
  {
    "id": "witch"
  },
  {
    "id": "fearmonger"
  },
  {
    "id": "vizier"
  },
  {
    "id": "vigormortis"
  },
  {
    "id": "fanggu"
  },
  {
    "id": "imp"
  }
]
