[
  {
    "id": "_meta",
    "name": "Banquet Receiving Line",
    "author": "LivFreeOrPie / Bill Pz"
  },
  {
    "id": "philosopher"
  },
  {
    "id": "artist"
  },
  {
    "id": "fisherman"
  },
  {
    "id": "savant"
  },
  {
    "id": "cannibal"
  },
  {
    "id": "minstrel"
  },
  {
    "id": "butler"
  },
  {
    "id": "klutz"
  },
  {
    "id": "marionette"
  },
  {
    "id": "scarletwoman"
  },
  {
    "id": "imp"
  },
  {
    "id": "djinn"
  },
  {
    "id": "sentinel"
  },
  {
    "id": "toymaker"
  }
]
