[
  {
    "id": "_meta",
    "name": "浮かぶ夢、沈む世界",
    "author": "Etreides"
  },
  {
    "id": "investigator"
  },
  {
    "id": "shugenja"
  },
  {
    "id": "pixie"
  },
  {
    "id": "balloonist"
  },
  {
    "id": "snakecharmer"
  },
  {
    "id": "dreamer"
  },
  {
    "id": "oracle"
  },
  {
    "id": "savant"
  },
  {
    "id": "amnesiac"
  },
  {
    "id": "nightwatchman"
  },
  {
    "id": "alchemist"
  },
  {
    "id": "magician"
  },
  {
    "id": "atheist"
  },
  {
    "id": "drunk"
  },
  {
    "id": "lunatic"
  },
  {
    "id": "recluse"
  },
  {
    "id": "mutant"
  },
  {
    "id": "mezepheles"
  },
  {
    "id": "cerenovus"
  },
  {
    "id": "pithag"
  },
  {
    "id": "vizier"
  },
  {
    "id": "organgrinder"
  },
  {
    "id": "lilmonsta"
  },
  {
    "id": "fanggu"
  },
  {
    "id": "legion"
  },
  {
    "id": "beggar"
  },
  {
    "id": "bishop"
  },
  {
    "id": "bonecollector"
  },
  {
    "id": "deviant"
  },
  {
    "id": "voudon"
  },
  {
    "id": "djinn"
  },
  {
    "id": "spiritofivory"
  }
]
