[
  {
    "id": "_meta",
    "name": "Turning A Blind Eye",
    "author": "NotChris"
  },
  {
    "id": "noble"
  },
  {
    "id": "investigator"
  },
  {
    "id": "bountyhunter"
  },
  {
    "id": "general"
  },
  {
    "id": "balloonist"
  },
  {
    "id": "oracle"
  },
  {
    "id": "amnesiac"
  },
  {
    "id": "juggler"
  },
  {
    "id": "slayer"
  },
  {
    "id": "soldier"
  },
  {
    "id": "ravenkeeper"
  },
  {
    "id": "poppygrower"
  },
  {
    "id": "mayor"
  },
  {
    "id": "puzzlemaster"
  },
  {
    "id": "tinker"
  },
  {
    "id": "heretic"
  },
  {
    "id": "drunk"
  },
  {
    "id": "moonchild"
  },
  {
    "id": "pithag"
  },
  {
    "id": "psychopath"
  },
  {
    "id": "assassin"
  },
  {
    "id": "organgrinder"
  },
  {
    "id": "ojo"
  },
  {
    "id": "fanggu"
  },
  {
    "id": "legion"
  }
]
