[
  {
    "id": "_meta",
    "name": "The  Looking Glass",
    "author": "Emma"
  },
  {
    "id": "knight"
  },
  {
    "id": "noble"
  },
  {
    "id": "pixie"
  },
  {
    "id": "balloonist"
  },
  {
    "id": "fortuneteller"
  },
  {
    "id": "monk"
  },
  {
    "id": "savant"
  },
  {
    "id": "amnesiac"
  },
  {
    "id": "engineer"
  },
  {
    "id": "fisherman"
  },
  {
    "id": "farmer"
  },
  {
    "id": "cannibal"
  },
  {
    "id": "atheist"
  },
  {
    "id": "plaguedoctor"
  },
  {
    "id": "klutz"
  },
  {
    "id": "hatter"
  },
  {
    "id": "puzzlemaster"
  },
  {
    "id": "widow"
  },
  {
    "id": "poisoner"
  },
  {
    "id": "organgrinder"
  },
  {
    "id": "vizier"
  },
  {
    "id": "nodashii"
  },
  {
    "id": "imp"
  },
  {
    "id": "ojo"
  },
  {
    "id": "fanggu"
  }
]
