[
  {
    "id": "_meta",
    "name": "Great Mystery",
    "author": "Jerry08"
  },
  {
    "id": "investigator"
  },
  {
    "id": "clockmaker"
  },
  {
    "id": "librarian"
  },
  {
    "id": "pixie"
  },
  {
    "id": "chambermaid"
  },
  {
    "id": "dreamer"
  },
  {
    "id": "snakecharmer"
  },
  {
    "id": "mathematician"
  },
  {
    "id": "fortuneteller"
  },
  {
    "id": "flowergirl"
  },
  {
    "id": "nightwatchman"
  },
  {
    "id": "poppygrower"
  },
  {
    "id": "cannibal"
  },
  {
    "id": "acrobat"
  },
  {
    "id": "recluse"
  },
  {
    "id": "mutant"
  },
  {
    "id": "drunk"
  },
  {
    "id": "cerenovus"
  },
  {
    "id": "scarletwoman"
  },
  {
    "id": "boomdandy"
  },
  {
    "id": "marionette"
  },
  {
    "id": "pukka"
  },
  {
    "id": "lleech"
  },
  {
    "id": "nodashii"
  },
  {
    "id": "vortox"
  }
]
