[
  {
    "id": "_meta",
    "name": "",
    "author": ""
  },
  {
    "id": "noble"
  },
  {
    "id": "librarian"
  },
  {
    "id": "empath"
  },
  {
    "id": "highpriestess"
  },
  {
    "id": "gambler"
  },
  {
    "id": "monk"
  },
  {
    "id": "exorcist"
  },
  {
    "id": "gossip"
  },
  {
    "id": "savant"
  },
  {
    "id": "artist"
  },
  {
    "id": "seamstress"
  },
  {
    "id": "soldier"
  },
  {
    "id": "farmer"
  },
  {
    "id": "tinker"
  },
  {
    "id": "mutant"
  },
  {
    "id": "drunk"
  },
  {
    "id": "hatter"
  },
  {
    "id": "godfather"
  },
  {
    "id": "cerenovus"
  },
  {
    "id": "scarletwoman"
  },
  {
    "id": "marionette"
  },
  {
    "id": "nodashii"
  },
  {
    "id": "imp"
  },
  {
    "id": "ojo"
  },
  {
    "id": "shabaloth"
  }
]
