[
  {
    "id": "_meta",
    "logo": "https://clocktower.online/img/artist.e76624f3.png",
    "name": "Art Gallery",
    "author": "Le Codex"
  },
  {
    "id": "librarian"
  },
  {
    "id": "noble"
  },
  {
    "id": "pixie"
  },
  {
    "id": "savant"
  },
  {
    "id": "philosopher"
  },
  {
    "id": "huntsman"
  },
  {
    "id": "seamstress"
  },
  {
    "id": "artist"
  },
  {
    "id": "juggler"
  },
  {
    "id": "magician"
  },
  {
    "id": "minstrel"
  },
  {
    "id": "mayor"
  },
  {
    "id": "cannibal"
  },
  {
    "id": "mutant"
  },
  {
    "id": "puzzlemaster"
  },
  {
    "id": "recluse"
  },
  {
    "id": "damsel"
  },
  {
    "id": "godfather"
  },
  {
    "id": "mezepheles"
  },
  {
    "id": "poisoner"
  },
  {
    "id": "witch"
  },
  {
    "id": "fearmonger"
  },
  {
    "id": "pukka"
  },
  {
    "id": "imp"
  },
  {
    "id": "vortox"
  }
]
