[
  {
    "id": "_meta",
    "name": "Family Don't End With Blood",
    "author": "Bees"
  },
  {
    "id": "librarian"
  },
  {
    "id": "grandmother"
  },
  {
    "id": "preacher"
  },
  {
    "id": "fortuneteller"
  },
  {
    "id": "monk"
  },
  {
    "id": "exorcist"
  },
  {
    "id": "gossip"
  },
  {
    "id": "savant"
  },
  {
    "id": "slayer"
  },
  {
    "id": "professor"
  },
  {
    "id": "alchemist"
  },
  {
    "id": "pacifist"
  },
  {
    "id": "cannibal"
  },
  {
    "id": "saint"
  },
  {
    "id": "recluse"
  },
  {
    "id": "heretic"
  },
  {
    "id": "drunk"
  },
  {
    "id": "poisoner"
  },
  {
    "id": "devilsadvocate"
  },
  {
    "id": "fearmonger"
  },
  {
    "id": "assassin"
  },
  {
    "id": "scarletwoman"
  },
  {
    "id": "eviltwin"
  },
  {
    "id": "imp"
  },
  {
    "id": "shabaloth"
  },
  {
    "id": "bishop"
  },
  {
    "id": "bonecollector"
  },
  {
    "id": "butcher"
  },
  {
    "id": "harlot"
  },
  {
    "id": "scapegoat"
  },
  {
    "id": "angel"
  },
  {
    "id": "hellslibrarian"
  },
  {
    "id": "sentinel"
  }
]
