[
  {
    "id": "_meta",
    "name": "Panic At The Disco By Fall Out Boy",
    "author": "Avery"
  },
  {
    "id": "noble"
  },
  {
    "id": "shugenja"
  },
  {
    "id": "pixie"
  },
  {
    "id": "general"
  },
  {
    "id": "dreamer"
  },
  {
    "id": "villageidiot"
  },
  {
    "id": "monk"
  },
  {
    "id": "artist"
  },
  {
    "id": "slayer"
  },
  {
    "id": "seamstress"
  },
  {
    "id": "philosopher"
  },
  {
    "id": "soldier"
  },
  {
    "id": "mayor"
  },
  {
    "id": "goon"
  },
  {
    "id": "saint"
  },
  {
    "id": "mutant"
  },
  {
    "id": "drunk"
  },
  {
    "id": "barber"
  },
  {
    "id": "widow"
  },
  {
    "id": "cerenovus"
  },
  {
    "id": "fearmonger"
  },
  {
    "id": "baron"
  },
  {
    "id": "ojo"
  },
  {
    "id": "vortox"
  },
  {
    "id": "fanggu"
  }
]
