[
  {
    "id": "_meta",
    "name": "Drunk and Disorderly V4"
  },
  {
    "id": "innkeeper"
  },
  {
    "id": "undertaker"
  },
  {
    "id": "chambermaid"
  },
  {
    "id": "dreamer"
  },
  {
    "id": "mathematician"
  },
  {
    "id": "savant"
  },
  {
    "id": "philosopher"
  },
  {
    "id": "seamstress"
  },
  {
    "id": "noble"
  },
  {
    "id": "steward"
  },
  {
    "id": "bountyhunter"
  },
  {
    "id": "minstrel"
  },
  {
    "id": "farmer"
  },
  {
    "id": "drunk"
  },
  {
    "id": "goon"
  },
  {
    "id": "mutant"
  },
  {
    "id": "barber"
  },
  {
    "id": "sweetheart"
  },
  {
    "id": "poisoner"
  },
  {
    "id": "godfather"
  },
  {
    "id": "cerenovus"
  },
  {
    "id": "pithag"
  },
  {
    "id": "imp"
  },
  {
    "id": "nodashii"
  },
  {
    "id": "vigormortis"
  },
  {
    "id": "thief"
  },
  {
    "id": "bureaucrat"
  },
  {
    "id": "gunslinger"
  },
  {
    "id": "judge"
  },
  {
    "id": "bonecollector"
  }
]
