[
  {
    "id": "_meta",
    "name": "Time Is Ticking",
    "author": "Delta"
  },
  {
    "id": "clockmaker"
  },
  {
    "id": "investigator"
  },
  {
    "id": "librarian"
  },
  {
    "id": "washerwoman"
  },
  {
    "id": "balloonist"
  },
  {
    "id": "fortuneteller"
  },
  {
    "id": "sailor"
  },
  {
    "id": "monk"
  },
  {
    "id": "towncrier"
  },
  {
    "id": "undertaker"
  },
  {
    "id": "artist"
  },
  {
    "id": "slayer"
  },
  {
    "id": "ravenkeeper"
  },
  {
    "id": "golem"
  },
  {
    "id": "drunk"
  },
  {
    "id": "moonchild"
  },
  {
    "id": "recluse"
  },
  {
    "id": "widow"
  },
  {
    "id": "poisoner"
  },
  {
    "id": "assassin"
  },
  {
    "id": "boomdandy"
  },
  {
    "id": "fanggu"
  },
  {
    "id": "imp"
  },
  {
    "id": "vortox"
  },
  {
    "id": "pukka"
  },
  {
    "id": "apprentice"
  },
  {
    "id": "bonecollector"
  },
  {
    "id": "bureaucrat"
  },
  {
    "id": "scapegoat"
  },
  {
    "id": "thief"
  }
]
