[
  {
    "id": "_meta",
    "name": "Alchemical Romance",
    "author": "Hodge"
  },
  {
    "id": "knight"
  },
  {
    "id": "bountyhunter"
  },
  {
    "id": "pixie"
  },
  {
    "id": "chambermaid"
  },
  {
    "id": "balloonist"
  },
  {
    "id": "fortuneteller"
  },
  {
    "id": "gossip"
  },
  {
    "id": "courtier"
  },
  {
    "id": "seamstress"
  },
  {
    "id": "huntsman"
  },
  {
    "id": "alchemist"
  },
  {
    "id": "magician"
  },
  {
    "id": "virgin"
  },
  {
    "id": "ogre"
  },
  {
    "id": "sweetheart"
  },
  {
    "id": "plaguedoctor"
  },
  {
    "id": "recluse"
  },
  {
    "id": "damsel"
  },
  {
    "id": "godfather"
  },
  {
    "id": "poisoner"
  },
  {
    "id": "spy"
  },
  {
    "id": "scarletwoman"
  },
  {
    "id": "eviltwin"
  },
  {
    "id": "vigormortis"
  },
  {
    "id": "fanggu"
  }
]
