[
  {
    "id": "_meta",
    "name": "The Devil You've Known",
    "author": "Zadon"
  },
  {
    "id": "noble"
  },
  {
    "id": "grandmother"
  },
  {
    "id": "pixie"
  },
  {
    "id": "empath"
  },
  {
    "id": "dreamer"
  },
  {
    "id": "flowergirl"
  },
  {
    "id": "towncrier"
  },
  {
    "id": "oracle"
  },
  {
    "id": "savant"
  },
  {
    "id": "artist"
  },
  {
    "id": "philosopher"
  },
  {
    "id": "alchemist"
  },
  {
    "id": "poppygrower"
  },
  {
    "id": "snitch"
  },
  {
    "id": "klutz"
  },
  {
    "id": "golem"
  },
  {
    "id": "moonchild"
  },
  {
    "id": "lunatic"
  },
  {
    "id": "spy"
  },
  {
    "id": "fearmonger"
  },
  {
    "id": "pithag"
  },
  {
    "id": "goblin"
  },
  {
    "id": "alhadikhia"
  },
  {
    "id": "vortox"
  },
  {
    "id": "leviathan"
  }
]
