[
  {
    "id": "_meta",
    "name": "My Mum Thinks I'm Special",
    "author": "Tam and Sean"
  },
  {
    "id": "steward"
  },
  {
    "id": "snakecharmer"
  },
  {
    "id": "balloonist"
  },
  {
    "id": "fortuneteller"
  },
  {
    "id": "king"
  },
  {
    "id": "flowergirl"
  },
  {
    "id": "undertaker"
  },
  {
    "id": "innkeeper"
  },
  {
    "id": "savant"
  },
  {
    "id": "nightwatchman"
  },
  {
    "id": "professor"
  },
  {
    "id": "choirboy"
  },
  {
    "id": "mayor"
  },
  {
    "id": "goon"
  },
  {
    "id": "sweetheart"
  },
  {
    "id": "klutz"
  },
  {
    "id": "barber"
  },
  {
    "id": "poisoner"
  },
  {
    "id": "cerenovus"
  },
  {
    "id": "vizier"
  },
  {
    "id": "marionette"
  },
  {
    "id": "alhadikhia"
  }
]
