[
  {
    "id": "_meta",
    "name": "The Only Thing They Fear Is You",
    "author": "Brockwell"
  },
  {
    "id": "noble"
  },
  {
    "id": "shugenja"
  },
  {
    "id": "pixie"
  },
  {
    "id": "highpriestess"
  },
  {
    "id": "dreamer"
  },
  {
    "id": "fortuneteller"
  },
  {
    "id": "monk"
  },
  {
    "id": "savant"
  },
  {
    "id": "artist"
  },
  {
    "id": "slayer"
  },
  {
    "id": "seamstress"
  },
  {
    "id": "farmer"
  },
  {
    "id": "cannibal"
  },
  {
    "id": "goon"
  },
  {
    "id": "klutz"
  },
  {
    "id": "drunk"
  },
  {
    "id": "hatter"
  },
  {
    "id": "widow"
  },
  {
    "id": "witch"
  },
  {
    "id": "fearmonger"
  },
  {
    "id": "scarletwoman"
  },
  {
    "id": "boomdandy"
  },
  {
    "id": "kazali"
  },
  {
    "id": "nodashii"
  },
  {
    "id": "vortox"
  },
  {
    "id": "bootlegger"
  }
]
