[
  {
    "id": "_meta",
    "name": "Picking Flowers in the Dark",
    "author": ""
  },
  {
    "id": "grandmother"
  },
  {
    "id": "librarian"
  },
  {
    "id": "pixie"
  },
  {
    "id": "general"
  },
  {
    "id": "mathematician"
  },
  {
    "id": "flowergirl"
  },
  {
    "id": "undertaker"
  },
  {
    "id": "gossip"
  },
  {
    "id": "philosopher"
  },
  {
    "id": "slayer"
  },
  {
    "id": "juggler"
  },
  {
    "id": "cannibal"
  },
  {
    "id": "sage"
  },
  {
    "id": "ogre"
  },
  {
    "id": "moonchild"
  },
  {
    "id": "plaguedoctor"
  },
  {
    "id": "mutant"
  },
  {
    "id": "zealot"
  },
  {
    "id": "godfather"
  },
  {
    "id": "widow"
  },
  {
    "id": "marionette"
  },
  {
    "id": "scarletwoman"
  },
  {
    "id": "yaggababble"
  },
  {
    "id": "imp"
  },
  {
    "id": "lleech"
  }
]
