[
  {
    "id": "_meta",
    "name": "You Can Run, But You Can’t Hide",
    "author": "Moe"
  },
  {
    "id": "librarian"
  },
  {
    "id": "bountyhunter"
  },
  {
    "id": "pixie"
  },
  {
    "id": "balloonist"
  },
  {
    "id": "villageidiot"
  },
  {
    "id": "monk"
  },
  {
    "id": "exorcist"
  },
  {
    "id": "lycanthrope"
  },
  {
    "id": "alsaahir"
  },
  {
    "id": "huntsman"
  },
  {
    "id": "cannibal"
  },
  {
    "id": "banshee"
  },
  {
    "id": "magician"
  },
  {
    "id": "lunatic"
  },
  {
    "id": "drunk"
  },
  {
    "id": "zealot"
  },
  {
    "id": "damsel"
  },
  {
    "id": "harpy"
  },
  {
    "id": "fearmonger"
  },
  {
    "id": "widow"
  },
  {
    "id": "summoner"
  },
  {
    "id": "scarletwoman"
  },
  {
    "id": "pukka"
  },
  {
    "id": "imp"
  },
  {
    "id": "ojo"
  }
]
