[
  {
    "id": "_meta",
    "name": "Evil Septuplets",
    "author": "MyMy"
  },
  {
    "id": "shugenja"
  },
  {
    "id": "highpriestess"
  },
  {
    "id": "general"
  },
  {
    "id": "villageidiot"
  },
  {
    "id": "towncrier"
  },
  {
    "id": "gambler"
  },
  {
    "id": "gossip"
  },
  {
    "id": "savant"
  },
  {
    "id": "alsaahir"
  },
  {
    "id": "seamstress"
  },
  {
    "id": "alchemist"
  },
  {
    "id": "cannibal"
  },
  {
    "id": "amnesiac"
  },
  {
    "id": "atheist"
  },
  {
    "id": "lunatic"
  },
  {
    "id": "golem"
  },
  {
    "id": "barber"
  },
  {
    "id": "puzzlemaster"
  },
  {
    "id": "assassin"
  },
  {
    "id": "eviltwin"
  },
  {
    "id": "boomdandy"
  },
  {
    "id": "baron"
  },
  {
    "id": "yaggababble"
  },
  {
    "id": "vortox"
  },
  {
    "id": "legion"
  }
]
