[
  {
    "id": "_meta",
    "name": "Is it loud in here? 1.1",
    "author": "Bunnybaby"
  },
  {
    "id": "washerwoman"
  },
  {
    "id": "librarian"
  },
  {
    "id": "towncrier"
  },
  {
    "id": "monk"
  },
  {
    "id": "gossip"
  },
  {
    "id": "alsaahir"
  },
  {
    "id": "artist"
  },
  {
    "id": "fisherman"
  },
  {
    "id": "juggler"
  },
  {
    "id": "cannibal"
  },
  {
    "id": "amnesiac"
  },
  {
    "id": "banshee"
  },
  {
    "id": "tealady"
  },
  {
    "id": "drunk"
  },
  {
    "id": "hatter"
  },
  {
    "id": "snitch"
  },
  {
    "id": "puzzlemaster"
  },
  {
    "id": "harpy"
  },
  {
    "id": "fearmonger"
  },
  {
    "id": "psychopath"
  },
  {
    "id": "goblin"
  },
  {
    "id": "yaggababble"
  },
  {
    "id": "shabaloth"
  },
  {
    "id": "po"
  },
  {
    "id": "alhadikhia"
  },
  {
    "id": "spiritofivory"
  }
]
