[
  {
    "id": "_meta",
    "name": "Go Ahead and Break My Heart Again",
    "author": "InspirationFollows"
  },
  {
    "id": "steward"
  },
  {
    "id": "shugenja"
  },
  {
    "id": "pixie"
  },
  {
    "id": "highpriestess"
  },
  {
    "id": "towncrier"
  },
  {
    "id": "oracle"
  },
  {
    "id": "innkeeper"
  },
  {
    "id": "exorcist"
  },
  {
    "id": "alsaahir"
  },
  {
    "id": "fisherman"
  },
  {
    "id": "alchemist"
  },
  {
    "id": "sage"
  },
  {
    "id": "magician"
  },
  {
    "id": "ogre"
  },
  {
    "id": "plaguedoctor"
  },
  {
    "id": "damsel"
  },
  {
    "id": "puzzlemaster"
  },
  {
    "id": "marionette"
  },
  {
    "id": "goblin"
  },
  {
    "id": "scarletwoman"
  },
  {
    "id": "boffin"
  },
  {
    "id": "pukka"
  },
  {
    "id": "imp"
  },
  {
    "id": "bureaucrat"
  },
  {
    "id": "butcher"
  },
  {
    "id": "matron"
  },
  {
    "id": "judge"
  },
  {
    "id": "beggar"
  },
  {
    "id": "djinn"
  },
  {
    "id": "sentinel"
  }
]
