[
  {
    "id": "_meta",
    "name": "Press X to Doubt",
    "author": "Sir Felneus"
  },
  {
    "id": "knight"
  },
  {
    "id": "chef"
  },
  {
    "id": "sailor"
  },
  {
    "id": "balloonist"
  },
  {
    "id": "general"
  },
  {
    "id": "flowergirl"
  },
  {
    "id": "oracle"
  },
  {
    "id": "courtier"
  },
  {
    "id": "fisherman"
  },
  {
    "id": "juggler"
  },
  {
    "id": "farmer"
  },
  {
    "id": "minstrel"
  },
  {
    "id": "pacifist"
  },
  {
    "id": "recluse"
  },
  {
    "id": "sweetheart"
  },
  {
    "id": "barber"
  },
  {
    "id": "damsel"
  },
  {
    "id": "godfather"
  },
  {
    "id": "devilsadvocate"
  },
  {
    "id": "xaan"
  },
  {
    "id": "goblin"
  },
  {
    "id": "boffin"
  },
  {
    "id": "zombuul"
  },
  {
    "id": "vigormortis"
  },
  {
    "id": "lordoftyphon"
  }
]
