[
  {
    "id": "_meta",
    "name": "Etreidean Nights",
    "author": "Heylo"
  },
  {
    "id": "pixie"
  },
  {
    "id": "highpriestess"
  },
  {
    "id": "balloonist"
  },
  {
    "id": "villageidiot"
  },
  {
    "id": "snakecharmer"
  },
  {
    "id": "mathematician"
  },
  {
    "id": "fortuneteller"
  },
  {
    "id": "flowergirl"
  },
  {
    "id": "oracle"
  },
  {
    "id": "savant"
  },
  {
    "id": "philosopher"
  },
  {
    "id": "cannibal"
  },
  {
    "id": "amnesiac"
  },
  {
    "id": "butler"
  },
  {
    "id": "drunk"
  },
  {
    "id": "plaguedoctor"
  },
  {
    "id": "hatter"
  },
  {
    "id": "poisoner"
  },
  {
    "id": "spy"
  },
  {
    "id": "cerenovus"
  },
  {
    "id": "boffin"
  },
  {
    "id": "imp"
  },
  {
    "id": "kazali"
  },
  {
    "id": "vigormortis"
  },
  {
    "id": "vortox"
  },
  {
    "id": "thief"
  },
  {
    "id": "barista"
  },
  {
    "id": "apprentice"
  },
  {
    "id": "bootlegger"
  },
  {
    "id": "djinn"
  },
  {
    "id": "gardener"
  }
]
