[
  {
    "id": "_meta",
    "name": "Etymologically Distinct Fog of War",
    "author": "Backup"
  },
  {
    "id": "knight"
  },
  {
    "id": "investigator"
  },
  {
    "id": "shugenja"
  },
  {
    "id": "bountyhunter"
  },
  {
    "id": "general"
  },
  {
    "id": "king"
  },
  {
    "id": "lycanthrope"
  },
  {
    "id": "engineer"
  },
  {
    "id": "nightwatchman"
  },
  {
    "id": "soldier"
  },
  {
    "id": "choirboy"
  },
  {
    "id": "magician"
  },
  {
    "id": "poppygrower"
  },
  {
    "id": "lunatic"
  },
  {
    "id": "golem"
  },
  {
    "id": "plaguedoctor"
  },
  {
    "id": "zealot"
  },
  {
    "id": "harpy"
  },
  {
    "id": "witch"
  },
  {
    "id": "cerenovus"
  },
  {
    "id": "assassin"
  },
  {
    "id": "ojo"
  },
  {
    "id": "vortox"
  }
]
